sonic/__init__.py
sonic/__main__.py
sonic/filemap.yaml
sonic/skeleton/.env
sonic/skeleton/.gitignore
sonic/skeleton/README.md
sonic/skeleton/__init__.py
sonic/skeleton/main.py
sonic/skeleton/models.py
sonic/skeleton/requirements.txt
sonic/skeleton/schemas.py
sonic/skeleton/routes/__init__.py
sonic/skeleton/routes/test.py
sonic/skeleton/static/script.js
sonic/skeleton/static/style.css
sonic/skeleton/templates/index.html
sonic/skeleton/utils/__init__.py
sonic/skeleton/utils/helpers.py
sonic_generator-1.1.5.dist-info/METADATA
sonic_generator-1.1.5.dist-info/WHEEL
sonic_generator-1.1.5.dist-info/entry_points.txt
sonic_generator-1.1.5.dist-info/top_level.txt
sonic_generator-1.1.5.dist-info/RECORD
