Metadata-Version: 2.1
Name: sonic-generator
Version: 1.1.5
Summary: Automatically generate starter template for your FastPI projects in a jiffy.
Home-page: https://github.com/rexsimiloluwah/sonic-generator
Author: Similoluwa Okunowo
Author-email: rexsimiloluwa@gmail.com
License: MIT
Platform: UNKNOWN
Classifier: License :: OSI Approved :: MIT License
Classifier: Programming Language :: Python :: 3
Classifier: Programming Language :: Python :: 3.7
Requires-Dist: fastapi
Requires-Dist: aiofiles
Requires-Dist: pydantic
Requires-Dist: uvicorn
Requires-Dist: PyYAML
Requires-Dist: jinja2
Requires-Dist: colorama
